Utilies/Chrome.py
Utilies/MISC.py
Utilies/SFTP.py
Utilies/__init__.py
Utilies/selenium_certification.py
Utilies/test/__init__.py
Utilies/test/test_file.py
utilies-0.1.6.dist-info/METADATA
utilies-0.1.6.dist-info/WHEEL
utilies-0.1.6.dist-info/top_level.txt
utilies-0.1.6.dist-info/RECORD
